{"id":791504,"name":"","username":"BenjyBuilds","avatar_template":"/user_avatar/llllllll.co/benjybuilds/{size}/112987_2.png","created_at":"2026-04-29T07:10:19.945Z","cooked":"\u003cp\u003eBtw, have you considered using airfix (or similar) plastic bonding cement? It would probably work for plastic contacts that small if you use a needle\u003c/p\u003e","post_number":880,"post_type":1,"posts_count":846,"updated_at":"2026-04-29T07:10:38.637Z","reply_count":1,"reply_to_post_number":876,"quote_count":0,"incoming_link_count":0,"reads":274,"readers_count":273,"score":73.0,"yours":false,"topic_id":66795,"topic_slug":"te-stem-player","display_username":"","primary_group_name":null,"flair_name":null,"flair_url":null,"flair_bg_color":null,"flair_color":null,"flair_group_id":null,"badges_granted":[],"version":1,"can_edit":false,"can_delete":false,"can_recover":false,"can_see_hidden_post":false,"can_wiki":false,"user_title":null,"reply_to_user":{"id":12340,"username":"KHAGE","name":"K H A G E","avatar_template":"/user_avatar/llllllll.co/khage/{size}/107026_2.png"},"bookmarked":false,"raw":"Btw, have you considered using airfix (or similar) plastic bonding cement? It would probably work for plastic contacts that small if you use a needle","actions_summary":[{"id":2,"count":1}],"moderator":false,"admin":false,"staff":false,"user_id":17474,"hidden":false,"trust_level":0,"deleted_at":null,"user_deleted":false,"edit_reason":null,"can_view_edit_history":false,"wiki":false,"post_url":"/t/te-stem-player/66795/880","can_accept_answer":false,"can_unaccept_answer":false,"accepted_answer":false,"topic_accepted_answer":null}